{
  "id": "home",
  "label": "home",
  "repeatable": false,
  "status": true,
  "json": {
    "Main": {
      "slices": {
        "type": "Slices",
        "fieldset": "Slice Zone",
        "config": {
          "choices": {
            "hero_banner": {
              "type": "SharedSlice"
            },
            "introduction": {
              "type": "SharedSlice"
            },
            "image": {
              "type": "SharedSlice"
            },
            "screenshot_gallery": {
              "type": "SharedSlice"
            }
          }
        }
      }
    }
  }
}